{
  "main": {
    "id": "ba37dc0814fc0ebc",
    "type": "split",
    "children": [
      {
        "id": "e1998b01224c5831",
        "type": "tabs",
        "children": [
          {
            "id": "1632bcc037e3c3c8",
            "type": "leaf",
            "state": {
              "type": "markdown",
              "state": {
                "file": "README.md",
                "mode": "source",
                "source": false
              }
            }
          },
          {
            "id": "8e56aa5ac4ad51b2",
            "type": "leaf",
            "state": {
              "type": "markdown",
              "state": {
                "file": "자바스크립트/자바스크립트.md",
                "mode": "source",
                "source": false
              }
            }
          },
          {
            "id": "23c1ae21dc1859e5",
            "type": "leaf",
            "state": {
              "type": "markdown",
              "state": {
                "file": "_posts/2023-12-05-Monorepo Multi package.md",
                "mode": "source",
                "source": false
              }
            }
          },
          {
            "id": "a5f31af7f6859a69",
            "type": "leaf",
            "state": {
              "type": "markdown",
              "state": {
                "file": "_posts/2023-12-05-Monorepo Multi package.md",
                "mode": "source",
                "source": false
              }
            }
          }
        ],
        "currentTab": 3
      }
    ],
    "direction": "vertical"
  },
  "left": {
    "id": "c3b4c2190c891bcb",
    "type": "split",
    "children": [
      {
        "id": "ed19badadb567abb",
        "type": "tabs",
        "children": [
          {
            "id": "f604919dd48704a7",
            "type": "leaf",
            "state": {
              "type": "file-explorer",
              "state": {
                "sortOrder": "alphabetical"
              }
            }
          },
          {
            "id": "57b9e89d7ecff3d9",
            "type": "leaf",
            "state": {
              "type": "search",
              "state": {
                "query": "",
                "matchingCase": false,
                "explainSearch": false,
                "collapseAll": false,
                "extraContext": false,
                "sortOrder": "alphabetical"
              }
            }
          },
          {
            "id": "bd6efb644685a637",
            "type": "leaf",
            "state": {
              "type": "bookmarks",
              "state": {}
            }
          }
        ]
      }
    ],
    "direction": "horizontal",
    "width": 300
  },
  "right": {
    "id": "dfb7645d092a15d0",
    "type": "split",
    "children": [
      {
        "id": "e1e81cd611700f94",
        "type": "tabs",
        "children": [
          {
            "id": "2645ff928b90e533",
            "type": "leaf",
            "state": {
              "type": "backlink",
              "state": {
                "file": "_posts/2023-12-05-Monorepo Multi package.md",
                "collapseAll": false,
                "extraContext": false,
                "sortOrder": "alphabetical",
                "showSearch": false,
                "searchQuery": "",
                "backlinkCollapsed": false,
                "unlinkedCollapsed": true
              }
            }
          },
          {
            "id": "1288a4e731656d71",
            "type": "leaf",
            "state": {
              "type": "outgoing-link",
              "state": {
                "file": "_posts/2023-12-05-Monorepo Multi package.md",
                "linksCollapsed": false,
                "unlinkedCollapsed": true
              }
            }
          },
          {
            "id": "8e311e021933074e",
            "type": "leaf",
            "state": {
              "type": "tag",
              "state": {
                "sortOrder": "frequency",
                "useHierarchy": true
              }
            }
          },
          {
            "id": "0edab784389c74c9",
            "type": "leaf",
            "state": {
              "type": "outline",
              "state": {
                "file": "_posts/2023-12-05-Monorepo Multi package.md"
              }
            }
          },
          {
            "id": "29c75c61e8dbd8e5",
            "type": "leaf",
            "state": {
              "type": "all-properties",
              "state": {
                "sortOrder": "frequency"
              }
            }
          }
        ]
      }
    ],
    "direction": "horizontal",
    "width": 300,
    "collapsed": true
  },
  "left-ribbon": {
    "hiddenItems": {
      "switcher:퀵 스위처 열기": false,
      "graph:그래프 뷰 열기": false,
      "canvas:새 캔버스 만들기": false,
      "daily-notes:오늘의 데일리 노트 열기": false,
      "templates:템플릿 삽입": false,
      "command-palette:명령어 팔레트 열기": false
    }
  },
  "active": "a5f31af7f6859a69",
  "lastOpenFiles": [
    "_posts/2023-12-05-Monorepo Multi project.md",
    "_posts/2023-12-05-Monorepo Multi package.md",
    "형상 관리/Monorepo Multi package.md",
    "자바스크립트/함수형 프로그래밍과 클래스.md",
    "자바스크립트/AbortController(nodejs).md",
    "To Do.md",
    "형상 관리",
    "코드에 대한 인식의 변화.md",
    "데이터 형에 따른 데이터베이스 선택.md",
    "함수형 프로그래밍/함수형 프로그래밍.md",
    "Prisma 걷어내기.md",
    "SQL 문을 코드에 넣으면?.md",
    "함수형 프로그래밍/this.md",
    "자바스크립트/자바스크립트.md",
    "README.md",
    "함수형 프로그래밍/함수형 helper 메서드 만들기.md",
    "_posts/함수형 프로그래밍/2023-12-03-함수형 helper 메서드 만들기.md",
    "함수형 프로그래밍/모나드(Monad).md",
    "_posts/2023-11-25-nodejs 예외 처리.md",
    "자바스크립트/nodejs 예외 처리.md",
    "_posts/2023-11-24-제 1 정규화.md",
    "데이터베이스/제 1 정규화.md",
    "데이터베이스",
    "Solving.md",
    "테스트/어떤 테스트 코드를 작성 해야 할까?.md",
    "토이 프로젝트/QB(Query Builder).md",
    "테스트",
    "함수형 프로그래밍/펑터(Functor).md",
    "자바스크립트",
    "_posts/함수형 프로그래밍/2023-10-24-범주(Category Theory).md",
    "_includes/head.html~",
    "_includes/head.html",
    "_includes",
    "_site/jekyll/update/welcome-to-jekyll/index.html",
    "_site/jekyll/update/welcome-to-jekyll",
    "_site/jekyll/update",
    "토이 프로젝트/images/스크린샷 2023-09-27 21-46-01.png"
  ]
}